polygon/__init__.py
polygon/api.py
polygon_client/__init__.py
polygon_client/api.py
polygon_client-1.0a6.dist-info/LICENSE
polygon_client-1.0a6.dist-info/METADATA
polygon_client-1.0a6.dist-info/WHEEL
polygon_client-1.0a6.dist-info/top_level.txt
polygon_client-1.0a6.dist-info/RECORD
