Metadata-Version: 2.1
Name: polygon-client
Version: 1.0a6
Summary: Python wrapper for Polygon API (polygon.codeforces.com)
Home-page: https://github.com/citxx/polygon-py
Author: Artem Tabolin
Author-email: artemtab@gmail.com
License: UNKNOWN
Platform: UNKNOWN
Classifier: Programming Language :: Python :: 3
Classifier: License :: OSI Approved :: MIT License
Classifier: Operating System :: OS Independent
Requires-Python: >=3.5
